mini_engine.py
mini_game_engine-1.0.0.dist-info/METADATA
mini_game_engine-1.0.0.dist-info/WHEEL
mini_game_engine-1.0.0.dist-info/top_level.txt
mini_game_engine-1.0.0.dist-info/RECORD
